GTC/LU.py
GTC/__init__.py
GTC/archive.py
GTC/archive_old.py
GTC/context.py
GTC/core.py
GTC/deprecated.py
GTC/formatting.py
GTC/function.py
GTC/json_format.py
GTC/json_format_old.py
GTC/lib.py
GTC/linear_algebra.py
GTC/named_tuples.py
GTC/nodes.py
GTC/persistence.py
GTC/reporting.py
GTC/type_a.py
GTC/type_b.py
GTC/uncertain_array.py
GTC/vector.py
GTC/xml_format.py
GTC/schema/gtc_v_1_3_5.json
GTC/schema/gtc_v_1_5_0.json
GTC/schema/gtc_v_1_5_0.xsd
GTC-1.5.1.dist-info/AUTHORS.rst
GTC-1.5.1.dist-info/LICENSE
GTC-1.5.1.dist-info/METADATA
GTC-1.5.1.dist-info/WHEEL
GTC-1.5.1.dist-info/top_level.txt
GTC-1.5.1.dist-info/RECORD
