Metadata-Version: 2.1
Name: GTC
Version: 1.5.1
Summary: The GUM Tree Calculator for Python
Home-page: https://github.com/MSLNZ/GTC
Author: Measurement Standards Laboratory of New Zealand
Author-email: info@measurement.govt.nz
License: MIT
Platform: any
Classifier: Development Status :: 4 - Beta
Classifier: Intended Audience :: Science/Research
Classifier: Intended Audience :: Developers
Classifier: License :: OSI Approved :: MIT License
Classifier: Operating System :: OS Independent
Classifier: Programming Language :: Python :: 2
Classifier: Programming Language :: Python :: 2.7
Classifier: Programming Language :: Python :: 3
Classifier: Programming Language :: Python :: 3.5
Classifier: Programming Language :: Python :: 3.6
Classifier: Programming Language :: Python :: 3.7
Classifier: Programming Language :: Python :: 3.8
Classifier: Programming Language :: Python :: 3.9
Classifier: Programming Language :: Python :: 3.10
Classifier: Programming Language :: Python :: 3.11
Classifier: Programming Language :: Python :: 3.12
Classifier: Topic :: Software Development
Classifier: Topic :: Scientific/Engineering
License-File: LICENSE
License-File: AUTHORS.rst
Requires-Dist: numpy >=1.13.0
Requires-Dist: scipy
Provides-Extra: docs
Requires-Dist: sphinx >2 ; extra == 'docs'
Requires-Dist: sphinx-rtd-theme >0.5 ; extra == 'docs'
Provides-Extra: tests
Requires-Dist: pytest >=4.4 ; extra == 'tests'
Requires-Dist: pytest-cov ; extra == 'tests'
Requires-Dist: jsonschema ; extra == 'tests'
Requires-Dist: lxml ; extra == 'tests'
